{
  "T01": {"status": "done", "attempts": 1, "worktree": "../20260627212423-w1t01", "branch": "blueprint/01-backend-deps-and-fernet", "last_error": null},
  "T02": {"status": "done", "attempts": 1, "worktree": "../20260627212423-w1t02", "branch": "blueprint/02-frontend-deps-and-tokens", "last_error": null},
  "T03": {"status": "done", "attempts": 1, "worktree": "../20260627212423-w1t03", "branch": "blueprint/03-base-primitives-a", "last_error": null},
  "T04": {"status": "done", "attempts": 1, "worktree": "../20260627212423-w1t04", "branch": "blueprint/04-model-skeletons", "last_error": null},
  "T05": {"status": "done", "attempts": 1, "worktree": "../20260627212423-w2t05", "branch": "blueprint/05-sql-guard-module", "last_error": null},
  "T06": {"status": "done", "attempts": 1, "worktree": "../20260627212423-w2t06", "branch": "blueprint/06-dp-models-complete", "last_error": null},
  "T07": {"status": "done", "attempts": 1, "worktree": "../20260627212423-w2t07", "branch": "blueprint/07-kb-models-complete", "last_error": null},
  "T08": {"status": "done", "attempts": 1, "worktree": "../20260627212423-w2t08", "branch": "blueprint/08-sql-editor-primitive", "last_error": null},
  "T09": {"status": "done", "attempts": 1, "worktree": "../20260627212423-w3t09", "branch": "blueprint/09-dp-kb-repositories", "last_error": null},
  "T10": {"status": "done", "attempts": 1, "worktree": "../20260627212423-w3t10", "branch": "blueprint/10-dp-kb-schemas", "last_error": null},
  "T11": {"status": "done", "attempts": 1, "worktree": "../20260627212423-w3t11", "branch": "blueprint/11-result-grid-schema-tree", "last_error": null},
  "T12": {"status": "done", "attempts": 1, "worktree": "../20260627212423-w3t12", "branch": "blueprint/12-data-table-primitive", "last_error": null},
  "T13": {"status": "done", "attempts": 1, "worktree": "../20260627212423-w4t13", "branch": "blueprint/13-dp-datasource-service", "last_error": null},
  "T14": {"status": "done", "attempts": 2, "worktree": "../20260627212423-w4t14", "branch": "blueprint/14-dp-query-service", "last_error": null},
  "T15": {"status": "done", "attempts": 2, "worktree": "../20260627212423-w4t15", "branch": "blueprint/15-dp-chat-service", "last_error": null},
  "T16": {"status": "done", "attempts": 1, "worktree": "../20260627212423-w4t16", "branch": "blueprint/16-kb-service", "last_error": null},
  "T17": {"status": "done", "attempts": 1, "worktree": "../20260627212423-w5t17", "branch": "blueprint/17-dp-routers", "last_error": null},
  "T18": {"status": "done", "attempts": 1, "worktree": "../20260627212423-w5t18", "branch": "blueprint/18-kb-routers", "last_error": null},
  "T19": {"status": "done", "attempts": 1, "worktree": "../20260627212423-w5t19", "branch": "blueprint/19-frontend-services-stores", "last_error": null},
  "T20": {"status": "done", "attempts": 1, "worktree": "../20260627212423-w5t20", "branch": "blueprint/20-app-routes-menu", "last_error": null},
  "T21": {"status": "done", "attempts": 1, "worktree": "../20260627212423-w6t21", "branch": "blueprint/21-page-sources-list", "last_error": null},
  "T22": {"status": "done", "attempts": 1, "worktree": "../20260627212423-w6t22", "branch": "blueprint/22-page-source-detail", "last_error": null},
  "T23": {"status": "done", "attempts": 1, "worktree": "../20260627212423-w6t23", "branch": "blueprint/23-kb-sublib-pages", "last_error": null},
  "T24": {"status": "done", "attempts": 1, "worktree": "../20260627212423-w6t24", "branch": "blueprint/24-kb-search-page", "last_error": null},
  "_integration": {"backend_w2": "blueprint/int-w2-backend", "frontend_w2": "blueprint/int-w2-frontend", "backend_w3": "blueprint/int-w3-backend", "frontend_w3": "blueprint/int-w3-frontend", "backend_w4": "blueprint/int-w4-backend", "backend_w5": "blueprint/int-w5-backend", "frontend_w5": "blueprint/int-w5-frontend", "frontend_w6": "blueprint/int-w6-frontend", "full_w8": "blueprint/int-full-w8", "full_w9": "blueprint/int-full-w9"},
  "T25": {"status": "pending", "attempts": 0, "worktree": null, "branch": null, "last_error": null},
  "T26": {"status": "pending", "attempts": 0, "worktree": null, "branch": null, "last_error": null},
  "T27": {"status": "pending", "attempts": 0, "worktree": null, "branch": null, "last_error": null},
  "T28": {"status": "pending", "attempts": 0, "worktree": null, "branch": null, "last_error": null},
  "T34": {"status": "done", "attempts": 1, "worktree": "../20260627212423-w9t34", "branch": "blueprint/34-db-migration-agent-looper", "commit": "0e29af4", "tests": "14 passed", "last_error": null},
  "T35": {"status": "done", "attempts": 1, "worktree": "../20260627212423-w9t35", "branch": "blueprint/35-discovery-writer-publish", "commit": "7ab5b7c", "tests": "18 passed", "last_error": null},
  "T36": {"status": "done", "attempts": 1, "worktree": "../20260627212423-w9t36", "branch": "blueprint/36-test-endpoint-integration", "commit": "235c457", "tests": "9 passed", "last_error": null},
  "T37": {"status": "done", "attempts": 1, "worktree": "../20260627212423-w9t37", "branch": "blueprint/37-compute-node-autodisco", "commit": "6a32f59", "tests": "5 passed", "last_error": null}
}
